{
	"info": {
		"_postman_id": "d0ef38bc-3a09-45f8-aaa2-f01889c09997",
		"name": "Gift Certificates",
		"schema": "https://schema.getpostman.com/json/collection/v2.1.0/collection.json"
	},
	"item": [
		{
			"name": "Tags",
			"item": [
				{
					"name": "All",
					"request": {
						"method": "GET",
						"header": [],
						"url": {
							"raw": "http://localhost:8080/Gradle___com_epam___certificates_war/api/tags",
							"protocol": "http",
							"host": [
								"localhost"
							],
							"port": "8080",
							"path": [
								"Gradle___com_epam___certificates_war",
								"api",
								"tags"
							]
						}
					},
					"response": []
				},
				{
					"name": "First Tag",
					"request": {
						"method": "GET",
						"header": [],
						"url": {
							"raw": "http://localhost:8080/Gradle___com_epam___certificates_war/api/tags/1",
							"protocol": "http",
							"host": [
								"localhost"
							],
							"port": "8080",
							"path": [
								"Gradle___com_epam___certificates_war",
								"api",
								"tags",
								"1"
							]
						}
					},
					"response": []
				},
				{
					"name": "Create valid Tag",
					"request": {
						"method": "POST",
						"header": [],
						"body": {
							"mode": "raw",
							"raw": "{\r\n    \"name\": \"fouth tag\"\r\n}",
							"options": {
								"raw": {
									"language": "json"
								}
							}
						},
						"url": {
							"raw": "http://localhost:8080/Gradle___com_epam___certificates_war/api/tags",
							"protocol": "http",
							"host": [
								"localhost"
							],
							"port": "8080",
							"path": [
								"Gradle___com_epam___certificates_war",
								"api",
								"tags"
							]
						}
					},
					"response": []
				},
				{
					"name": "Attempt to create invalid Tag",
					"request": {
						"method": "POST",
						"header": [],
						"body": {
							"mode": "raw",
							"raw": "{\r\n    \"name\": \"tag!\"\r\n}",
							"options": {
								"raw": {
									"language": "json"
								}
							}
						},
						"url": {
							"raw": "http://localhost:8080/Gradle___com_epam___certificates_war/api/tags",
							"protocol": "http",
							"host": [
								"localhost"
							],
							"port": "8080",
							"path": [
								"Gradle___com_epam___certificates_war",
								"api",
								"tags"
							]
						}
					},
					"response": []
				},
				{
					"name": "Attempt to create existing Tag",
					"request": {
						"method": "POST",
						"header": [],
						"body": {
							"mode": "raw",
							"raw": "{\r\n    \"name\": \"first tag\"\r\n}",
							"options": {
								"raw": {
									"language": "json"
								}
							}
						},
						"url": {
							"raw": "http://localhost:8080/Gradle___com_epam___certificates_war/api/tags",
							"protocol": "http",
							"host": [
								"localhost"
							],
							"port": "8080",
							"path": [
								"Gradle___com_epam___certificates_war",
								"api",
								"tags"
							]
						}
					},
					"response": []
				},
				{
					"name": "Delete Tag",
					"request": {
						"method": "DELETE",
						"header": [],
						"url": {
							"raw": "http://localhost:8080/Gradle___com_epam___certificates_war/api/tags/4",
							"protocol": "http",
							"host": [
								"localhost"
							],
							"port": "8080",
							"path": [
								"Gradle___com_epam___certificates_war",
								"api",
								"tags",
								"4"
							]
						}
					},
					"response": []
				},
				{
					"name": "Attempt to delete non-existent Tag",
					"request": {
						"method": "DELETE",
						"header": [],
						"url": {
							"raw": "http://localhost:8080/Gradle___com_epam___certificates_war/api/tags/11",
							"protocol": "http",
							"host": [
								"localhost"
							],
							"port": "8080",
							"path": [
								"Gradle___com_epam___certificates_war",
								"api",
								"tags",
								"11"
							]
						}
					},
					"response": []
				}
			]
		},
		{
			"name": "Gift Certificates",
			"item": [
				{
					"name": "List",
					"item": [
						{
							"name": "All",
							"request": {
								"method": "GET",
								"header": [],
								"url": {
									"raw": "http://localhost:8080/Gradle___com_epam___certificates_war/api/giftCertificates",
									"protocol": "http",
									"host": [
										"localhost"
									],
									"port": "8080",
									"path": [
										"Gradle___com_epam___certificates_war",
										"api",
										"giftCertificates"
									]
								}
							},
							"response": []
						},
						{
							"name": "All by Tag name",
							"request": {
								"method": "GET",
								"header": [],
								"url": {
									"raw": "http://localhost:8080/Gradle___com_epam___certificates_war/api/giftCertificates?tagName=second",
									"protocol": "http",
									"host": [
										"localhost"
									],
									"port": "8080",
									"path": [
										"Gradle___com_epam___certificates_war",
										"api",
										"giftCertificates"
									],
									"query": [
										{
											"key": "tagName",
											"value": "second"
										}
									]
								}
							},
							"response": []
						},
						{
							"name": "All by invalid Tag name",
							"request": {
								"method": "GET",
								"header": [],
								"url": {
									"raw": "http://localhost:8080/Gradle___com_epam___certificates_war/api/giftCertificates?tagName=second!",
									"protocol": "http",
									"host": [
										"localhost"
									],
									"port": "8080",
									"path": [
										"Gradle___com_epam___certificates_war",
										"api",
										"giftCertificates"
									],
									"query": [
										{
											"key": "tagName",
											"value": "second!"
										}
									]
								}
							},
							"response": []
						},
						{
							"name": "All by Gift Certificate name",
							"request": {
								"method": "GET",
								"header": [],
								"url": {
									"raw": "http://localhost:8080/Gradle___com_epam___certificates_war/api/giftCertificates?certificateName=certificate first and second",
									"protocol": "http",
									"host": [
										"localhost"
									],
									"port": "8080",
									"path": [
										"Gradle___com_epam___certificates_war",
										"api",
										"giftCertificates"
									],
									"query": [
										{
											"key": "certificateName",
											"value": "certificate first and second"
										}
									]
								}
							},
							"response": []
						},
						{
							"name": "All by invalid Gift Certificate name",
							"request": {
								"method": "GET",
								"header": [],
								"url": {
									"raw": "http://localhost:8080/Gradle___com_epam___certificates_war/api/giftCertificates?certificateName=certificate first and second$",
									"protocol": "http",
									"host": [
										"localhost"
									],
									"port": "8080",
									"path": [
										"Gradle___com_epam___certificates_war",
										"api",
										"giftCertificates"
									],
									"query": [
										{
											"key": "certificateName",
											"value": "certificate first and second$"
										}
									]
								}
							},
							"response": []
						},
						{
							"name": "All by Gift Certificate description",
							"request": {
								"method": "GET",
								"header": [],
								"url": {
									"raw": "http://localhost:8080/Gradle___com_epam___certificates_war/api/giftCertificates?certificateDescription=certificate with",
									"protocol": "http",
									"host": [
										"localhost"
									],
									"port": "8080",
									"path": [
										"Gradle___com_epam___certificates_war",
										"api",
										"giftCertificates"
									],
									"query": [
										{
											"key": "certificateDescription",
											"value": "certificate with"
										}
									]
								}
							},
							"response": []
						},
						{
							"name": "All by invalid Gift Certificate description",
							"request": {
								"method": "GET",
								"header": [],
								"url": {
									"raw": "http://localhost:8080/Gradle___com_epam___certificates_war/api/giftCertificates?certificateDescription=certificate with$",
									"protocol": "http",
									"host": [
										"localhost"
									],
									"port": "8080",
									"path": [
										"Gradle___com_epam___certificates_war",
										"api",
										"giftCertificates"
									],
									"query": [
										{
											"key": "certificateDescription",
											"value": "certificate with$"
										}
									]
								}
							},
							"response": []
						},
						{
							"name": "All name ordering",
							"request": {
								"method": "GET",
								"header": [],
								"url": {
									"raw": "http://localhost:8080/Gradle___com_epam___certificates_war/api/giftCertificates?orderingName=DESC",
									"protocol": "http",
									"host": [
										"localhost"
									],
									"port": "8080",
									"path": [
										"Gradle___com_epam___certificates_war",
										"api",
										"giftCertificates"
									],
									"query": [
										{
											"key": "orderingName",
											"value": "DESC"
										}
									]
								}
							},
							"response": []
						},
						{
							"name": "All invalid name ordering",
							"request": {
								"method": "GET",
								"header": [],
								"url": {
									"raw": "http://localhost:8080/Gradle___com_epam___certificates_war/api/giftCertificates?orderingName=DESC!",
									"protocol": "http",
									"host": [
										"localhost"
									],
									"port": "8080",
									"path": [
										"Gradle___com_epam___certificates_war",
										"api",
										"giftCertificates"
									],
									"query": [
										{
											"key": "orderingName",
											"value": "DESC!"
										}
									]
								}
							},
							"response": []
						},
						{
							"name": "All creation date ordering",
							"request": {
								"method": "GET",
								"header": [],
								"url": {
									"raw": "http://localhost:8080/Gradle___com_epam___certificates_war/api/giftCertificates?orderingDate=DESC",
									"protocol": "http",
									"host": [
										"localhost"
									],
									"port": "8080",
									"path": [
										"Gradle___com_epam___certificates_war",
										"api",
										"giftCertificates"
									],
									"query": [
										{
											"key": "orderingDate",
											"value": "DESC"
										}
									]
								}
							},
							"response": []
						},
						{
							"name": "All invalid creation date ordering",
							"request": {
								"method": "GET",
								"header": [],
								"url": {
									"raw": "http://localhost:8080/Gradle___com_epam___certificates_war/api/giftCertificates?orderingDate=DESC!",
									"protocol": "http",
									"host": [
										"localhost"
									],
									"port": "8080",
									"path": [
										"Gradle___com_epam___certificates_war",
										"api",
										"giftCertificates"
									],
									"query": [
										{
											"key": "orderingDate",
											"value": "DESC!"
										}
									]
								}
							},
							"response": []
						},
						{
							"name": "All with all params",
							"request": {
								"method": "GET",
								"header": [],
								"url": {
									"raw": "http://localhost:8080/Gradle___com_epam___certificates_war/api/giftCertificates?certificateName=certificate&certificateDescription=certificate&orderingName=DESC&orderingDate=DESC",
									"protocol": "http",
									"host": [
										"localhost"
									],
									"port": "8080",
									"path": [
										"Gradle___com_epam___certificates_war",
										"api",
										"giftCertificates"
									],
									"query": [
										{
											"key": "certificateName",
											"value": "certificate"
										},
										{
											"key": "certificateDescription",
											"value": "certificate"
										},
										{
											"key": "orderingName",
											"value": "DESC"
										},
										{
											"key": "orderingDate",
											"value": "DESC"
										}
									]
								}
							},
							"response": []
						},
						{
							"name": "First Gift certificate",
							"request": {
								"method": "GET",
								"header": [],
								"url": {
									"raw": "http://localhost:8080/Gradle___com_epam___certificates_war/api/giftCertificates/1",
									"protocol": "http",
									"host": [
										"localhost"
									],
									"port": "8080",
									"path": [
										"Gradle___com_epam___certificates_war",
										"api",
										"giftCertificates",
										"1"
									]
								}
							},
							"response": []
						}
					]
				},
				{
					"name": "Create",
					"item": [
						{
							"name": "Gift certificate without Tags",
							"request": {
								"method": "POST",
								"header": [],
								"body": {
									"mode": "raw",
									"raw": "{\r\n    \"name\": \"certificate new\",\r\n    \"description\": \"certificate new\",\r\n    \"price\": 100.00,\r\n    \"duration\": 90\r\n}",
									"options": {
										"raw": {
											"language": "json"
										}
									}
								},
								"url": {
									"raw": "http://localhost:8080/Gradle___com_epam___certificates_war/api/giftCertificates",
									"protocol": "http",
									"host": [
										"localhost"
									],
									"port": "8080",
									"path": [
										"Gradle___com_epam___certificates_war",
										"api",
										"giftCertificates"
									]
								}
							},
							"response": []
						},
						{
							"name": "Gift certificate with existing Tag",
							"request": {
								"method": "POST",
								"header": [],
								"body": {
									"mode": "raw",
									"raw": "{\r\n    \"name\": \"certificate with second tag\",\r\n    \"description\": \"certificate\",\r\n    \"price\": 100.00,\r\n    \"duration\": 90,\r\n    \"tagsDto\": [\r\n            {\r\n                \"id\": 2,\r\n                \"name\": \"second tag\"\r\n            }\r\n        ]\r\n}",
									"options": {
										"raw": {
											"language": "json"
										}
									}
								},
								"url": {
									"raw": "http://localhost:8080/Gradle___com_epam___certificates_war/api/giftCertificates",
									"protocol": "http",
									"host": [
										"localhost"
									],
									"port": "8080",
									"path": [
										"Gradle___com_epam___certificates_war",
										"api",
										"giftCertificates"
									]
								}
							},
							"response": []
						},
						{
							"name": "Gift certificate with new Tag",
							"request": {
								"method": "POST",
								"header": [],
								"body": {
									"mode": "raw",
									"raw": "{\r\n    \"name\": \"certificate with new tag\",\r\n    \"description\": \"certificate\",\r\n    \"price\": 100.00,\r\n    \"duration\": 90,\r\n    \"tagsDto\": [\r\n            {\r\n                \"name\": \"new tag\"\r\n            }\r\n        ]\r\n}",
									"options": {
										"raw": {
											"language": "json"
										}
									}
								},
								"url": {
									"raw": "http://localhost:8080/Gradle___com_epam___certificates_war/api/giftCertificates",
									"protocol": "http",
									"host": [
										"localhost"
									],
									"port": "8080",
									"path": [
										"Gradle___com_epam___certificates_war",
										"api",
										"giftCertificates"
									]
								}
							},
							"response": []
						}
					]
				},
				{
					"name": "Edit",
					"item": [
						{
							"name": "Patch name",
							"request": {
								"method": "PATCH",
								"header": [],
								"body": {
									"mode": "raw",
									"raw": "{\r\n    \"name\": \"patched certificate new\"\r\n}",
									"options": {
										"raw": {
											"language": "json"
										}
									}
								},
								"url": {
									"raw": "http://localhost:8080/Gradle___com_epam___certificates_war/api/giftCertificates/1",
									"protocol": "http",
									"host": [
										"localhost"
									],
									"port": "8080",
									"path": [
										"Gradle___com_epam___certificates_war",
										"api",
										"giftCertificates",
										"1"
									]
								}
							},
							"response": []
						},
						{
							"name": "Patch Invalid name",
							"request": {
								"method": "PATCH",
								"header": [],
								"body": {
									"mode": "raw",
									"raw": "{\r\n    \"name\": \"certificate new!\"\r\n}",
									"options": {
										"raw": {
											"language": "json"
										}
									}
								},
								"url": {
									"raw": "http://localhost:8080/Gradle___com_epam___certificates_war/api/giftCertificates/1",
									"protocol": "http",
									"host": [
										"localhost"
									],
									"port": "8080",
									"path": [
										"Gradle___com_epam___certificates_war",
										"api",
										"giftCertificates",
										"1"
									]
								}
							},
							"response": []
						},
						{
							"name": "Patch description",
							"request": {
								"method": "PATCH",
								"header": [],
								"body": {
									"mode": "raw",
									"raw": "{\r\n    \"description\": \"patched certificate description\"\r\n}",
									"options": {
										"raw": {
											"language": "json"
										}
									}
								},
								"url": {
									"raw": "http://localhost:8080/Gradle___com_epam___certificates_war/api/giftCertificates/1",
									"protocol": "http",
									"host": [
										"localhost"
									],
									"port": "8080",
									"path": [
										"Gradle___com_epam___certificates_war",
										"api",
										"giftCertificates",
										"1"
									]
								}
							},
							"response": []
						},
						{
							"name": "Patch invalid description",
							"request": {
								"method": "PATCH",
								"header": [],
								"body": {
									"mode": "raw",
									"raw": "{\r\n    \"description\": \"patched certificate new \"\r\n}",
									"options": {
										"raw": {
											"language": "json"
										}
									}
								},
								"url": {
									"raw": "http://localhost:8080/Gradle___com_epam___certificates_war/api/giftCertificates/1",
									"protocol": "http",
									"host": [
										"localhost"
									],
									"port": "8080",
									"path": [
										"Gradle___com_epam___certificates_war",
										"api",
										"giftCertificates",
										"1"
									]
								}
							},
							"response": []
						},
						{
							"name": "Patch price",
							"request": {
								"method": "PATCH",
								"header": [],
								"body": {
									"mode": "raw",
									"raw": "{\r\n    \"price\": 100.01\r\n}",
									"options": {
										"raw": {
											"language": "json"
										}
									}
								},
								"url": {
									"raw": "http://localhost:8080/Gradle___com_epam___certificates_war/api/giftCertificates/1",
									"protocol": "http",
									"host": [
										"localhost"
									],
									"port": "8080",
									"path": [
										"Gradle___com_epam___certificates_war",
										"api",
										"giftCertificates",
										"1"
									]
								}
							},
							"response": []
						},
						{
							"name": "Patch invalid price",
							"request": {
								"method": "PATCH",
								"header": [],
								"body": {
									"mode": "raw",
									"raw": "{\r\n    \"price\": 0.03\r\n}",
									"options": {
										"raw": {
											"language": "json"
										}
									}
								},
								"url": {
									"raw": "http://localhost:8080/Gradle___com_epam___certificates_war/api/giftCertificates/1",
									"protocol": "http",
									"host": [
										"localhost"
									],
									"port": "8080",
									"path": [
										"Gradle___com_epam___certificates_war",
										"api",
										"giftCertificates",
										"1"
									]
								}
							},
							"response": []
						},
						{
							"name": "Patch duration",
							"request": {
								"method": "PATCH",
								"header": [],
								"body": {
									"mode": "raw",
									"raw": "{\r\n    \"duration\": 180\r\n}",
									"options": {
										"raw": {
											"language": "json"
										}
									}
								},
								"url": {
									"raw": "http://localhost:8080/Gradle___com_epam___certificates_war/api/giftCertificates/1",
									"protocol": "http",
									"host": [
										"localhost"
									],
									"port": "8080",
									"path": [
										"Gradle___com_epam___certificates_war",
										"api",
										"giftCertificates",
										"1"
									]
								}
							},
							"response": []
						},
						{
							"name": "Patch invalid duration",
							"request": {
								"method": "PATCH",
								"header": [],
								"body": {
									"mode": "raw",
									"raw": "{\r\n    \"duration\": -90\r\n}",
									"options": {
										"raw": {
											"language": "json"
										}
									}
								},
								"url": {
									"raw": "http://localhost:8080/Gradle___com_epam___certificates_war/api/giftCertificates/1",
									"protocol": "http",
									"host": [
										"localhost"
									],
									"port": "8080",
									"path": [
										"Gradle___com_epam___certificates_war",
										"api",
										"giftCertificates",
										"1"
									]
								}
							},
							"response": []
						},
						{
							"name": "Patch new Tags in list",
							"request": {
								"method": "PATCH",
								"header": [],
								"body": {
									"mode": "raw",
									"raw": "{\r\n    \"tagsDto\" : [\r\n            {\r\n                \"id\": 1,\r\n                \"name\": \"first tag\"\r\n            },\r\n            {\r\n                \"id\": 2,\r\n                \"name\": \"second tag\"\r\n            }\r\n        ]\r\n}",
									"options": {
										"raw": {
											"language": "json"
										}
									}
								},
								"url": {
									"raw": "http://localhost:8080/Gradle___com_epam___certificates_war/api/giftCertificates/3",
									"protocol": "http",
									"host": [
										"localhost"
									],
									"port": "8080",
									"path": [
										"Gradle___com_epam___certificates_war",
										"api",
										"giftCertificates",
										"3"
									]
								}
							},
							"response": []
						},
						{
							"name": "Patch without Tag in stored list",
							"request": {
								"method": "PATCH",
								"header": [],
								"body": {
									"mode": "raw",
									"raw": "{\r\n    \"tagsDto\" : [\r\n            {\r\n                \"id\": 1,\r\n                \"name\": \"first tag\"\r\n            }\r\n        ]\r\n}",
									"options": {
										"raw": {
											"language": "json"
										}
									}
								},
								"url": {
									"raw": "http://localhost:8080/Gradle___com_epam___certificates_war/api/giftCertificates/1",
									"protocol": "http",
									"host": [
										"localhost"
									],
									"port": "8080",
									"path": [
										"Gradle___com_epam___certificates_war",
										"api",
										"giftCertificates",
										"1"
									]
								}
							},
							"response": []
						},
						{
							"name": "Patch all fields",
							"request": {
								"method": "PATCH",
								"header": [],
								"body": {
									"mode": "raw",
									"raw": "{\r\n        \"id\": 1,\r\n        \"name\": \"certificate first and second tags new version\",\r\n        \"description\": \"certificate with first tag and second tag new version\",\r\n        \"price\": 49.99,\r\n        \"duration\": 99,\r\n        \"createDate\": \"2015-01-01T11:11:11.222\",\r\n        \"lastUpdateDate\": \"2031-01-01T11:11:11.222\",\r\n        \"tagsDto\": [\r\n            {\r\n                \"id\": 1,\r\n                \"name\": \"first tag\"\r\n            },\r\n            {\r\n                \"id\": 2,\r\n                \"name\": \"second tag\"\r\n            }\r\n        ]\r\n    }",
									"options": {
										"raw": {
											"language": "json"
										}
									}
								},
								"url": {
									"raw": "http://localhost:8080/Gradle___com_epam___certificates_war/api/giftCertificates/1",
									"protocol": "http",
									"host": [
										"localhost"
									],
									"port": "8080",
									"path": [
										"Gradle___com_epam___certificates_war",
										"api",
										"giftCertificates",
										"1"
									]
								}
							},
							"response": []
						}
					]
				},
				{
					"name": "Delete",
					"item": [
						{
							"name": "Delete Gift Certificate",
							"request": {
								"method": "DELETE",
								"header": [],
								"url": {
									"raw": "http://localhost:8080/Gradle___com_epam___certificates_war/api/giftCertificates/1",
									"protocol": "http",
									"host": [
										"localhost"
									],
									"port": "8080",
									"path": [
										"Gradle___com_epam___certificates_war",
										"api",
										"giftCertificates",
										"1"
									]
								}
							},
							"response": []
						},
						{
							"name": "Attempt to delete non-existing Gift Certificate",
							"request": {
								"method": "DELETE",
								"header": [],
								"url": {
									"raw": "http://localhost:8080/Gradle___com_epam___certificates_war/api/giftCertificates/111",
									"protocol": "http",
									"host": [
										"localhost"
									],
									"port": "8080",
									"path": [
										"Gradle___com_epam___certificates_war",
										"api",
										"giftCertificates",
										"111"
									]
								}
							},
							"response": []
						}
					]
				}
			]
		}
	]
}